tentaclio_snowflake/__init__.py
tentaclio_snowflake/__main__.py
tentaclio_snowflake/clients/__init__.py
tentaclio_snowflake/clients/snowflake_client.py
tentaclio_snowflake-0.0.3.dist-info/LICENSE.txt
tentaclio_snowflake-0.0.3.dist-info/METADATA
tentaclio_snowflake-0.0.3.dist-info/WHEEL
tentaclio_snowflake-0.0.3.dist-info/top_level.txt
tentaclio_snowflake-0.0.3.dist-info/RECORD
